<?xml version="1.0"?>
<!--<!DOCTYPE metadata SYSTEM "http://www.esri.com/metadata/esriprof80.dtd">-->
<metadata xml:lang="en"><Esri><CreaDate>20081216</CreaDate><CreaTime>14194400</CreaTime><SyncOnce>TRUE</SyncOnce><MetaID>{D78CD2F1-A629-4F73-9659-AE11FDE3B2B9}</MetaID></Esri><idinfo><citation><citeinfo><onlink Sync="TRUE">\\SNAKEHEAD\C$\Ag_Census\Export\mosaic_v9</onlink></citeinfo></citation></idinfo><distInfo><distributor><distorTran><onLineSrc><linkage Sync="TRUE">file://\\SNAKEHEAD\C$\Ag_Census\Export\mosaic_v9</linkage><protocol Sync="TRUE">Local Area Network</protocol></onLineSrc></distorTran></distributor></distInfo><dataqual><lineage><procstep><procdesc Sync="TRUE">Dataset copied.</procdesc><srcused Sync="TRUE">C:\Ag_Census\mosaic_v9</srcused><procdate Sync="TRUE">20081216</procdate><proctime Sync="TRUE">14194400</proctime></procstep></lineage></dataqual></metadata>
